{
	"configurations" : 
	[
		{
			"directories" : 
			[
				{
					"build" : ".",
					"jsonFile" : "directory-.-Debug-f5ebdc15457944623624.json",
					"minimumCMakeVersion" : 
					{
						"string" : "3.22"
					},
					"projectIndex" : 0,
					"source" : ".",
					"targetIndexes" : 
					[
						0,
						1
					]
				}
			],
			"name" : "Debug",
			"projects" : 
			[
				{
					"directoryIndexes" : 
					[
						0
					],
					"name" : "automat",
					"targetIndexes" : 
					[
						0,
						1
					]
				}
			],
			"targets" : 
			[
				{
					"directoryIndex" : 0,
					"id" : "automat::@6890427a1f51a3e7e1df",
					"jsonFile" : "target-automat-Debug-3f835f817e5520790f81.json",
					"name" : "automat",
					"projectIndex" : 0
				},
				{
					"directoryIndex" : 0,
					"id" : "glad::@6890427a1f51a3e7e1df",
					"jsonFile" : "target-glad-Debug-61e572e9c122b5697362.json",
					"name" : "glad",
					"projectIndex" : 0
				}
			]
		}
	],
	"kind" : "codemodel",
	"paths" : 
	{
		"build" : "/home/bublik/CLionProjects/automat/cmake-build-debug-coverage",
		"source" : "/home/bublik/CLionProjects/automat"
	},
	"version" : 
	{
		"major" : 2,
		"minor" : 3
	}
}
